.gitignore
LICENSE
README.md
Tests.py
setup.cfg
setup.py
usage.py
.github/FUNDING.yml
api/resource/application-local.yml
api/resource/application.yml
api/resource/notes.yml
api/resource/setting-up-raspberrypi.yml
python_framework/__init__.py
python_framework.egg-info/PKG-INFO
python_framework.egg-info/SOURCES.txt
python_framework.egg-info/dependency_links.txt
python_framework.egg-info/requires.txt
python_framework.egg-info/top_level.txt
python_framework/api/resource/__init__.py
python_framework/api/resource/example.json
python_framework/api/src/annotation/ConverterAnnotation.py
python_framework/api/src/annotation/EnumAnnotation.py
python_framework/api/src/annotation/GlobalExceptionAnnotation.py
python_framework/api/src/annotation/HelperAnnotation.py
python_framework/api/src/annotation/MapperAnnotation.py
python_framework/api/src/annotation/RepositoryAnnotation.py
python_framework/api/src/annotation/SchedulerAnnotation.py
python_framework/api/src/annotation/ServiceAnnotation.py
python_framework/api/src/annotation/ValidatorAnnotation.py
python_framework/api/src/annotation/client/ClientAnnotation.py
python_framework/api/src/annotation/client/EmitterAnnotation.py
python_framework/api/src/annotation/client/HttpClientAnnotation.py
python_framework/api/src/annotation/client/ListenerAnnotation.py
python_framework/api/src/constant/AuditoryConstant.py
python_framework/api/src/constant/ConfigurationKeyConstant.py
python_framework/api/src/constant/ControllerConstant.py
python_framework/api/src/constant/HealthCheckConstant.py
python_framework/api/src/constant/HttpClientConstant.py
python_framework/api/src/constant/JwtConstant.py
python_framework/api/src/constant/LogConstant.py
python_framework/api/src/constant/SchedulerConstant.py
python_framework/api/src/constant/StaticConstant.py
python_framework/api/src/constant/WeekDayConstant.py
python_framework/api/src/controller/ActuatorHealthController.py
python_framework/api/src/controller/DocumentationController.py
python_framework/api/src/converter/ActuatorHealthConverter.py
python_framework/api/src/converter/static/ConverterStatic.py
python_framework/api/src/converter/static/StaticConverter.py
