Metadata-Version: 2.1
Name: python-framework
Version: 0.4.48
Summary: Flask wrapper
Home-page: https://github.com/SamuelJansen/python-framework/
Download-URL: https://github.com/SamuelJansen/python-framework/archive/v0.4.48.tar.gz
Author: Samuel Jansen
Author-email: samuel.jansenn@gmail.com
License: MIT
Keywords: flask,sqlalchemy,open api,jwt,serializer,scheduler
Classifier: Development Status :: 3 - Alpha
Classifier: Intended Audience :: Developers
Classifier: Topic :: Software Development :: Build Tools
Classifier: License :: OSI Approved :: MIT License
Classifier: Programming Language :: Python :: 3.7
Requires-Python: >=3.7
License-File: LICENSE
